<?xml version="1.0" encoding="gb2312"?>
<!DOCTYPE beans PUBLIC "-//SPRING//DTD BEAN//EN" "http://www.springframework.org/dtd/spring-beans.dtd">

<beans>
<!--***********************dao配置***********************************************-->
	<bean id="wfReportDao" class="com.lc.dcwork.wfrpt.dao.jdbc.WfReportJdbcDao">
		<property name="dataSource"><ref bean="dataSource"/></property>
	</bean>


	<bean id="wfReportService" class="com.lc.dcwork.wfrpt.service.support.WfReportServiceImpl"> 
		<property name="wfReportDao"><ref bean="wfReportDao"/></property>   	
		<property name="transactionTemplate"><ref bean="jdbcTransactionTemplate"/></property>
		<property name="reportIdDao"><ref bean="reportIdDao"/></property>
		<property name="wfReportDefineDao"><ref bean="wfReportdefineDao"/></property>   	
	</bean>

<bean id="reportIdDao" class="net.mast.bsp.base.id.dao.jdbc.IncrementDao">
	<property name="dataSource"><ref bean="dataSource"/></property>
	<property name="id"><value>WF_REPORT_ID</value></property>
</bean>

<!--***********************查询配置开始********************************************-->
	<bean id="wfreportquery" class="net.mast.waf.mvc.CommonQueryCommand">
		<property name="mappings">
			<props>
				<prop key="success">jsp/dcwork/wfrpt/wf_report_query.jsp</prop>
			</props>
		</property>     
		<property name="collection"><ref bean="sqlPageCollection"/></property>
	</bean>
<!--***********************查询配置结束********************************************-->

<!--***********************视图对象View配置****************************************-->
	<bean id="wfReportView"  class="com.lc.dcwork.wfrpt.view.WfReportView" singleton="false"/>

<!--***********************cmd配置开始*********************************************-->
    <bean id="wfrptquery" class="com.lc.dcwork.wfrpt.cmd.WfReportCmd" singleton="false">
	    <property name="wfReportService"><ref bean="wfReportService"/></property>
	    <property name="view"><ref bean="wfReportView"/></property>
	    <property name="forwards">
	        <map>
	            <entry key="wfreportView"><ref bean="wfreportforward"/></entry>
	            <entry key="wfreportViewChain"><ref bean="wfreportforwardchain"/></entry>
	        </map>
		</property>
    </bean>
    <bean id="wfreport" class="com.lc.dcwork.wfrpt.cmd.WfReportCmd" singleton="false">
	    <property name="wfReportService"><ref bean="wfReportService"/></property>
	    <property name="view"><ref bean="wfReportView"/></property>
	    <property name="forwards">
	        <map>
	            <entry key="wfreportView"><ref bean="wfreportforward"/></entry>
	            <entry key="wfreportViewChain"><ref bean="wfreportforwardchain"/></entry>
	        </map>
		</property>
<!--***********************cmd拦截器*********************************************-->
		<property name="beforIntercept">
	        <list>
	            <ref bean="wf_report_interceptor"/>	           
	        </list>
     	</property>
    </bean>

<!--***********************cmd配置结束*********************************************-->

<!--***********************界面转向forward配置开始***********************************-->
    <bean id="wfreportforward" class="net.mast.waf.mvc.ServletDispatcherForward">
	    <property name="mappings">
			<props>		    		    
			    <prop key="detail">jsp/dcwork/wfrpt/wf_report_detail.jsp</prop>
			    <prop key="forinsert">jsp/dcwork/wfrpt/wf_report_forinsert.jsp</prop>
			    <prop key="forupdate">jsp/dcwork/wfrpt/wf_report_forupdate.jsp</prop>
			    <prop key="gettreeeditroot">jsp/dcwork/wfrpt/wfrpt_tree_edit_root.jsp</prop>
			    <prop key="gettreeeditbranch">jsp/dcwork/wfrpt/wfrpt_tree_edit_branch.jsp</prop>
			    <!--<prop key="gettreeeditbranch">jsp/dcwork/wfrpt/wf_report_detailForm.jsp</prop>-->
			    <prop key="detailForm">jsp/dcwork/wfrpt/wf_report_detailForm.jsp</prop>
			    <prop key="delete">jsp/dcwork/wfrpt/wf_report_delete.jsp</prop>
			    
			</props>
		</property>
	</bean>
    <bean id="wfreportforwardchain" class="net.mast.waf.mvc.ChainForward">
	    <property name="mappings">
			<map>
			    <entry key="success"><ref bean="wfreportquery"/></entry>
			</map>
		</property>
    </bean>
<!--***********************界面转向forward配置结束***********************************-->
<!--***********************拦截器***************************-->
		<bean id="wf_report_interceptor" class="net.mast.waf.interceptor.CollectionInterceptor">
	    	<property name="collections">
    	    	<map>
				<entry key="WFRPT_AREA_COLLECTION"><ref bean="WFRPT_AREA_COLLECTION"/></entry>
			</map>
    	</property>
	</bean>
	
<!--***********************同时在collentionSupport.xml 中添加***************************-->
		<bean id="WFRPT_AREA_COLLECTION" class="net.mast.waf.data.EnumCollection">
	    	<property name="enumName"><value>WFRPT.AREA</value></property>
	    	<property name="enumService"><ref bean="enumService"/></property>
		</bean>

</beans>
